xtream_diamonds/__init__.py
xtream_diamonds/challenge3/__init__.py
xtream_diamonds/challenge3/categorical_mappings.py
xtream_diamonds/challenge3/cli_arguments.py
xtream_diamonds/challenge3/configuration.py
xtream_diamonds/challenge3/dataset_ingestion.py
xtream_diamonds/challenge3/dataset_split.py
xtream_diamonds/challenge3/evaluation.py
xtream_diamonds/challenge3/main.py
xtream_diamonds/challenge3/serialization.py
xtream_diamonds/challenge3/training.py
xtream_diamonds/challenge4/__init__.py
xtream_diamonds/challenge4/cli_arguments.py
xtream_diamonds/challenge4/diamond.py
xtream_diamonds/challenge4/endpoints/prices_endpoint.py
xtream_diamonds/challenge4/endpoints/root_endpoint.py
xtream_diamonds/challenge4/main.py
xtream_diamonds/challenge4/model.py
xtream_diamonds/challenge4/parsing.py
xtream_diamonds/challenge4/request.py
xtream_diamonds/challenge4/server.py
xtream_diamonds-0.3.0.dist-info/METADATA
xtream_diamonds-0.3.0.dist-info/WHEEL
xtream_diamonds-0.3.0.dist-info/entry_points.txt
xtream_diamonds-0.3.0.dist-info/RECORD
