Metadata-Version: 2.1
Name: xtream-diamonds
Version: 0.3.0
Summary: Xtream Data Science Interview Assignment
License: MIT
Author: dpaletti
Author-email: dpaletti@gmail.com
Requires-Python: >=3.8,<4.0
Classifier: License :: OSI Approved :: MIT License
Classifier: Programming Language :: Python :: 3
Classifier: Programming Language :: Python :: 3.8
Classifier: Programming Language :: Python :: 3.9
Classifier: Programming Language :: Python :: 3.10
Classifier: Programming Language :: Python :: 3.11
Requires-Dist: fastapi (>=0.92.0,<0.93.0)
Requires-Dist: pandas (>=1.5.3,<2.0.0)
Requires-Dist: requests (>=2.28.2,<3.0.0)
Requires-Dist: scikit-learn (>=1.2.1,<2.0.0)
Requires-Dist: uvicorn[standard] (>=0.20.0,<0.21.0)
Requires-Dist: xgboost (>=1.7.3,<2.0.0)
